{
  "kind": "collectionType",
  "collectionName": "posts",
  "info": {
    "name": "Posts",
    "description": ""
  },
  "options": {
    "increments": true,
    "timestamps": true,
    "draftAndPublish": true
  },
  "pluginOptions": {},
  "attributes": {
    "page": {
      "type": "string",
      "required": true
    },
    "position": {
      "type": "integer",
      "required": true,
      "min": 1
    },
    "title": {
      "type": "string",
      "required": false
    },
    "description": {
      "type": "text"
    },
    "image": {
      "collection": "file",
      "via": "related",
      "allowedTypes": [
        "images",
        "videos"
      ],
      "plugin": "upload",
      "required": false,
      "pluginOptions": {}
    }
  }
}
